LICENSE
partial_fstring/__init__.py
partial_fstring/py.typed
partial_fstring-0.0.5.3.dist-info/LICENSE
partial_fstring-0.0.5.3.dist-info/METADATA
partial_fstring-0.0.5.3.dist-info/WHEEL
partial_fstring-0.0.5.3.dist-info/RECORD
